plotfair/__init__.py
plotfair/apple_clr_pallete.py
plotfair/apple_colors.clr
plotfair/colormaps.py
plotfair/colors.py
plotfair/colorsheet.csv
plotfair/interplot_presets.py
plotfair/plt_y.py
plotfair/presets.py
plotfair-0.1.0.dist-info/METADATA
plotfair-0.1.0.dist-info/WHEEL
plotfair-0.1.0.dist-info/licenses/LICENSE
plotfair-0.1.0.dist-info/RECORD
