Metadata-Version: 2.4
Name: plotfair
Version: 0.1.0
Summary: Beautiful color and plotting utilities using matplotlib & plotly
Project-URL: Homepage, https://github.com/barton-muller/plotfair
Project-URL: Documentation, https://plotfair.readthedocs.io
Project-URL: Repository, https://github.com/barton-muller/plotfair
Project-URL: Issues, https://github.com/barton-muller/plotfair/issues
Author: Barton Muller
License-Expression: MIT
License-File: LICENSE
Keywords: colormap,colors,data-science,matplotlib,plotly,plotting,visualization
Classifier: Development Status :: 3 - Alpha
Classifier: Intended Audience :: Developers
Classifier: Intended Audience :: Science/Research
Classifier: License :: OSI Approved :: MIT License
Classifier: Operating System :: OS Independent
Classifier: Programming Language :: Python :: 3
Classifier: Programming Language :: Python :: 3.9
Classifier: Programming Language :: Python :: 3.10
Classifier: Programming Language :: Python :: 3.11
Classifier: Programming Language :: Python :: 3.12
Classifier: Programming Language :: Python :: 3.13
Classifier: Topic :: Scientific/Engineering :: Visualization
Requires-Python: >=3.9
Requires-Dist: colorspacious
Requires-Dist: interplot>=1.1.1
Requires-Dist: matplotlib
Requires-Dist: numpy
Requires-Dist: plotly>=6.5.2
Requires-Dist: pyobjc-framework-cocoa; platform_system == 'Darwin'
Requires-Dist: scipy
Requires-Dist: seaborn
Provides-Extra: dev
Requires-Dist: mypy; extra == 'dev'
Requires-Dist: pytest; extra == 'dev'
Requires-Dist: pytest-cov; extra == 'dev'
Requires-Dist: ruff; extra == 'dev'
Provides-Extra: docs
Requires-Dist: sphinx; extra == 'docs'
Requires-Dist: sphinx-rtd-theme; extra == 'docs'
